{
  "calendar":{
    "day":{
      "monday":"Lundi",
      "tuesday":"Mardi",
      "wednesday":"Mercredi",
      "thursday":"Jeudi",
      "friday":"Vendredi",
      "saturday":"Samedi",
      "sunday":"Dimanche"
    },
    "day_short":{
      "mon":"Lun",
      "tue":"Mar",
      "wed":"Mer",
      "thu":"Jeu",
      "fri":"Ven",
      "sat":"Sam",
      "sun":"Dim"
    },
    "month":{
      "january":"Janvier",
      "february":"Février",
      "march":"Mars",
      "april":"Avril",
      "may":"Mai",
      "june":"Juin",
      "july":"Juillet",
      "august":"Août",
      "september":"Septembre",
      "october":"Octobre",
      "november":"Novembre",
      "december":"Décembre"
    },
    "next_month":"Mois suivant",
    "previous_month":"Mois précédent"
  },
  "change-password":{
    "heading":"Changer le mot de passe",
    "submit":"Changer le mot de passe",
    "success-message":"Le mot de passe a été changé"
  },
  "choose-account":{
    "heading":"Sélectionner un compte",
    "remove":"Éditer la liste",
    "remove-selected":"Supprimer sélectionnés"
  },
  "confirm-personality":{
    "heading":"Confirmer personnalité",
    "subheading":"Merci d'attendre la vérification du compte",
    "success-message":"Votre compte a été vérifié"
  },
  "contact-admin":{
    "describe-problem":"Décrire votre problème",
    "email-helper":"L'adresse à laquelle vous recevrez les réponses",
    "heading":"Contacter administrateur",
    "submit":"Envoyer message",
    "success-message":"Administrateur a été prévenu",
    "tel":"Merci d'indiquer votre numéro de télphone mobile"
  },
  "create-account":{
    "alternative-email":"Email alternative",
    "domain":"Domaine",
    "full-name":"Nom complet",
    "heading":"Créer un compte",
    "last-step":"Dernière étape",
    "next-step":"Prochaine étape"
  },
  "error":{
    "invalid_login":"Nom d'utilisateur ou mot de passe incorrect. Merci de réessayer.",
    "expired":"Session expirée",
    "connection":"Impossible de contacter le serveur. Merci de vérifier la connexion Internet ou contacter votre administrateur.",
    "servererror":"Impossible d'accéder au service. Merci de réessayer ou contacter votre administrateur.",
    "overloaded":"Le serveur est actuellement surchargé. Merci de réessayer ou contacter votre administrateur.",
    "wc_disabled":"WebClient est désactivé.",
    "invalid_rsa":"Impossible de créer le mot de passe RSA.",
    "no_db":"Erreur de connexion à la base de données",
    "no_data":"Aucune donnée",
    "access_error":"Impossible d'accéder au dossier mail, merci de contacter votre administrateur.",
    "ip_mismatch":"Votre adress IP a changé, vous allez être déconnecté. Pour éviter cette déconnexion, merci d'utiliser le protocole HTTPs.",
    "sso_login_not_allowed":"Login SSO interdit",
    "sso_unable_to_use":"Impossible d'utiliser SSO",
    "sso_error":"Erreur durant la connexion en mode SSO",
    "auth_login_invalid":"Nom d'utilisateur ou mot de passe invalide",
    "account_already_exists":"Compte existe déjà",
    "account_alternative_email":"Compte n'a pas d'adresse email alternative. Merci de contacter l'administrateur.",
    "account_disabled_1":"Connexion impossible à cause de restriction sur les IP",
    "account_disabled_2":"Connexion impossible car le compte est désactivé",
    "account_disabled_3":"Connexion impossible car le mot de passe a expiré",
    "account_disabled_4":"Connexion impossible car le compte a expiré",
    "account_disabled_5":"Connexion impossible à cause du mode d'accès SMTP",
    "account_disabled_6":"Connexion impossible à cause du mode d'accès POP\/IMAP",
    "account_disabled_7":"Connexion impossible car le compte ne supporte qu'IMAP",
    "account_disabled_8":"Connexion impossible car le compte ne supporte que POP3",
    "account_disabled_9":"Connexion impossible car pas d'accès au WebClient",
    "account_disabled_10":"Connexion impossible à cause de mode d'accès",
    "account_disabled_11":"Connexion impossible car login au domaine est désactivé",
    "account_disabled_12":"Connexion impossible car le domaine a expiré",
    "account_disabled_13":"Connexion impossible à cause de licence",
    "account_invalid":"Compte invalide",
    "account_does_not_exist":"Compte spécifié n'existe pas",
    "account_missing_required_property":"Au moins une des propriétés obligatoires est manquante",
    "account_no_password":"Mot de passe manquant ou vide",
    "account_no_username":"Nom d'utilisateur manquant ou vide",
    "account_no_domain":"Domaine manquant",
    "account_password_policy":"Mot de passe n'est pas conforme à la stratégie des mots de passe",
    "account_signup_disabled":"Inscription désactivé",
    "account_signup_disabled_ip":"Administrateur a interdit l'inscription depuis votre IP",
    "auth_digest_expired":"Login expiré. Merci de vous connecter à nouveau.",
    "auth_two_factor_invalid":"Code vérification invalide",
    "auth_webadmin_session_not_found":"Session WebAdmin pas trouvée",
    "captcha_confirmation":"Code de sécurité erroné",
    "contact_support_no_admin_email":"Administrateur n'a pas configuré une adresse email",
    "db_auto_create":"Impossible de créer la base de données",
    "db_create_sqlitefile":"Impossible de créer le fichier SQLITE (.DB)",
    "db_create_tables":"Impossible de créer les tables",
    "db_invalid_statement":"Type de requête invalide",
    "domain_invalid":"Domaine invalide",
    "folder_get_list":"Impossible d'obtenir la liste de dossiers",
    "folder_open":"Impossible d'ouvrir le dossier",
    "group_open":"Impossible d'ouvrir le groupe",
    "groupware_authenticate":"Échec de login au Groupware",
    "groupware_db_connection":"Groupware ne peut pas se connecter à sa base de données",
    "groupware_timeout":"Temporisation Groupware dépassée",
    "groupware_upgrade_task":"Mise à jour du service Groupware en cours. Veuillez essayer plus tard.",
    "guest_invalid_hash":"Code de vérification erroné",
    "gw_init_error":"Erreur d'initialisation GroupWare",
    "language_path_not_found":"Chemin vers la langue pas trouvé",
    "language-not-found":"Fichier langue pas trouvé",
    "logdir_create":"Impossible de créer le répertoire des journaux",
    "login_account_valid":"Compte invalide",
    "login_invalid":"Nom d'utilisateur invalide",
    "login_invalid_keypair":"Échec de la validation RSA. Veuillez réessayer.",
    "login_ip_invalid":"Restriction sur IP de login",
    "migration_in_progress":"Migration du compte en cours. Veuillez réessayer plus tard.",
    "missing_request_params":"Paramètres manquants dans la requête",
    "no_teamchat_folders":"Connexion impossible à cause du dossier TeamChat manquant",
    "password_not_changed":"Le nouveau mot de passe ne peut être le même que l'ancien",
    "personality_confirmation_invalid_hashid":"Impossible de vérifier l'adresse email (hash invalide)",
    "personality_confirmation_invalid_user":"Impossible de confirmer l'adresse email (utilisateur invalide)",
    "reset_disabled":"Changement du mot de passe est interdit",
    "reset_password_invalid_hashid":"Hash ID invalide",
    "reset_password_no_hash":"Hash ID invalide",
    "reset_password_uid_file":"Fichier UID n'existe pas",
    "rsa_create_key_pair":"Impossible de créer la paire de clé RSA",
    "session_cookie_mismatch":"Cookie de session ne correspond pas",
    "session_expired":"Session expirée",
    "session_ip_mismatch":"IP de session ne correspond pas",
    "session_mismatch":"Session ne correspond pas",
    "session_no_user":"Utilisateur de session ne peut être récupéré",
    "setting_file_corrupted":"Paramètres serveur du WebMail sont corrompus. Merci de contacter votre administrateur.",
    "signup_verification_failed_sms":"Impossible d'envoyer la vérification par SMS",
    "signup_verification_failed_email":"Impossible d'envoyer la vérification par email",
    "signup_verification_not_initialized":"Vérification pas initialisée",
    "signup_verification_failed":"Échec de vérification",
    "storage_get_dom":"Impossible de charger le fichier de paramètres",
    "unavailable":"Temporairement indisponible",
    "unspecified":"Serveur a retourné l'erreur **%{error}**",
    "user_settings_global":"Impossible de charger les paramètres",
    "wm_disabled":"WebClient est désactivé"
  },
  "forgot-password":{
    "heading":"Mot de passe oublié ?",
    "submit":"Envoyez-moi les instructions",
    "success-message":"Email envoyé à votre adresse email alternative",
    "success-message-guest":"Email envoyé à votre adresse email"
  },
  "gateway-login":{
    "subheading":"Se connecter avec un compte administrateur pour gérer les domaines et les utilisateurs",
    "success-message":"Vous avez reçu un email contenant un lien sécurisé. Ce lien vous permettra pendant un temps limité d'accéder à la gestion de vos spams."
  },
  "generic":{
    "back":"Précédent",
    "cancel":"Annuler",
    "captcha-generate":"Générer nouveau",
    "check-account":"Re-vérifier votre compte",
    "choose-different-account":"Sélectionner un autre compte",
    "confirm":"Confirmer",
    "contact-admin":"Contacter administrateur",
    "copyright":"Réalisé par IceWarp",
    "create-acc":"Créer un compte",
    "done":"Terminé",
    "email":"Adresse email",
    "error":"Erreur",
    "female":"Femme",
    "find_out_more":"Pour savoir davantage sur IceWarp, visiter [www.icewarp.fr](\/\/www.icewarp.fr)",
    "fullscreen-enter":"Mode plein écran",
    "fullscreen-exit":"Quitter mode plein écran",
    "have-account":"Vous possédez un compte ?",
    "dont-have-account":"Vous n'avez pas encore de compte ?",
    "hide":"Masquer",
    "male":"Homme",
    "next":"Suivant",
    "not-you":"Pas vous ?",
    "password":"Mot de passe",
    "password-confirm":"Confirmer mot de passe",
    "password-current":"Mot de passe actuel",
    "password-new":"Nouveau mot de passe",
    "password-policy":"Stratégie des mots de passe",
    "retry":"Ré-essayer",
    "save-password":"Enregistrer le nouveau mot de passe",
    "search":"Rechercher",
    "security-code":"Code de sécurité",
    "send":"Envoyer",
    "show":"Afficher",
    "sign-in":"Connexion",
    "sign-with-another-acc":"Utiliser un autre compte",
    "skip":"Passer",
    "success":"Succès",
    "undefined":"Pas défini",
    "understand":"OK. J'ai compris",
    "undisclosed_participant":"Participant non divulgué",
    "username":"Nom d'utilisateur"
  },
  "guest-verify":{
    "heading":"Vérification du compte invité",
    "subheading":"Merci d'attendre la vérification de votre compte",
    "success-message":"Votre compte a été vérifié"
  },
  "interface":{
    "label":"Interface",
    "desktop":"Desktop",
    "tablet":"Tablette",
    "phone":"Mobile"
  },
  "personal":{
    "heading":"Informations personnelles",
    "nickname":"Surnom",
    "birthday":"Anniversaire",
    "company":"Société",
    "job":"Fonction",
    "profession":"Profession",
    "mobile-phone":"Téléphone Mobile",
    "work-phone":"Téléphone bureau",
    "home-phone":"Téléphone domicile",
    "im":"Messagerie instantanée",
    "gender":"Sexe",
    "homepage":"Page Web"
  },
  "reset-password":{
    "heading":"Changer mot de passe",
    "success-message":"Mot de passe a été changé"
  },
  "set-password":{
    "code_sent_to":"Code de vérification a été envoyé à *%{to}*.",
    "verification_code":"Code de vérification",
    "heading":"Vous avez presque terminé!",
    "submit":"Créer un compte",
    "success-message":"Le compte a été créé"
  },
  "sign-in-generic":{
    "heading":{
      "webclient":"Connexion au WebClient",
      "webadmin":"Connexion au WebAdmin"
    }
  },
  "sign-in-password":{
    "forgot":"Mot de passe oublié ?",
    "remember":"Maintenir la connexion"
  },
  "tc-actions":{
    "heading":"Actions du bouton Plus",
    "subheading":"Gérer facilement toutes les actions TeamChatavec le bouton '+'"
  },
  "tc-check-email":{
    "heading":"Vérifier votre email",
    "subheading":"Vérifier votre adresse email et utiliser la\"\"combinaison de votre adresse email et mot de passe pour rejoindre\"\" et entrer en conversation avec les autres utilisateurs de la salle TeamChat **%{room}**",
    "submit":"Aller à la page de connexion",
    "success-message":"Email a été vérifié"
  },
  "tc-collaboration":{
    "heading":"Collaboration des équipes",
    "subheading":"Échanger des idées, des fichiers ou autres données et participer en temps réel aux discussions de plusieurs groupes."
  },
  "tc-join":{
    "heading":"Se joindre à notre TeamChat",
    "subheading":"%{name} vous a invité pour rejoindre la salle TeamChat _%{room}_",
    "submit":"Vérifier mon adresse email",
    "success-message":"Vous avez rejoint la salle %{room}",
    "username":"Nom",
    "username-helper":"Ajouter votre nom tel qu'il sera vu dans TeamChat",
    "what-is-teamchat":"Qu'est-ce TeamChat ?"
  },
  "tc-share":{
    "heading":"Partager facilement",
    "subheading":"Glisser - Déposer tout document ou média - partager et éditer sans quitter l'application"
  },
  "title":{
    "webadmin":"IceWarp WebAdmin",
    "webclient":"IceWarp WebClient"
  },
  "touch-id":{
    "heading":"Se connecter avec touch ID",
    "use-password":"Utiliser plutôt le mot de passe"
  },
  "two_step":{
    "verification_code":"Code de vérification",
    "heading":"Validation en deux étapes",
    "subheading":"Merci d'entrer le code de 6 chiffres affiché dans l'application IceWarp Authenticator",
    "subheading-phone":"Merci d'entrer le code de 6 chiffres reçu sur le téléphone dont le numéro se termine par -%{phone}"
  },
  "validation":{
    "alpha_chars":"Le champ doit contenir au minumum %{amount} caractères de l'alphabet||||Le champ doit contenir au minumum %{amount} caractères de l'alphabet",
    "email":"Email invalide",
    "empty":"Champ ne peut être vide",
    "length":"La longueur doit être %{amount} caractères",
    "min_length":"La longueur minimum est %{amount} caractères",
    "non_alpha_num_chars":"Le champ doit contenir au minimum %{amount} caractères non-alphanumériques||||Le champ doit contenir au minimum %{amount} caractères non-alphanumériques",
    "numeric_chars":"Le champ doit contenir au minimum %{amount} chiffres||||Le champ doit contenir au minimum %{amount} chiffres",
    "passwords-no-match":"Les mots de passe ne sont pas identiques",
    "upper_alpha_chars":"Le champ doit contenir au minimum %{amount} caractères majuscules||||Le champ doit contenir au minimum %{amount} caractères majuscules",
    "user_alias":"Le champ ne peut pas contenir le nom d'utilisateur"
  },
  "wm-join":{
    "already-member":"Déjà membre",
    "audio-help":"Aide audio",
    "heading":"Joindre notre WebMeeting",
    "join-webmeeting":"Joindre WebMeeting",
    "subheading":"WebMeeting créé par %{name} est prêt",
    "subheading-prepare":"En attente des informations du WebMeeting",
    "success-message":"Vous avez rejoint la salle %{room}",
    "username":"Nom",
    "username-helper":"Ajouter le nom tel qu'il sera vu dans le WebMeeting"
  },
  "wm":{
    "device-error":"Erreur d'appareil",
    "error":"Une erreur s'est produite pendant le WebMeeting",
    "hang-up":"Racrocher",
    "hang-up-confirm":"Êtes-vous certain de vouloir quitter ce WebMeeting ?",
    "maximize":"Aggrandir la fenêtre",
    "microphone-denied":"Accès au micro n'est pas autorisé",
    "microphone-denied-helper":"Pas de possibilité de parler pendant ce WebMeeting",
    "no-microphone-detected":"Pas de micro trouvé",
    "phone-number":"Numéro de téléphone",
    "restore":"Restaurer la fenêtre",
    "screen-share-started":"Démarrage du partage d'écran",
    "screen-share-stopped":"Partage d'écran arrêté",
    "unsupported":"Ce navigateur ne supporte pas WebRTC",
    "unsupported-text":"[Plus information](%{link})",
    "user-joined":"Utilisateur **%{name}** a rejoint le WebMeeting",
    "user-left":"Utilisateur **%{name}** a quitté le WebMeeting",
    "meeting-ended":"Fin du WebMeeting",
    "welcome-message":"Bienvenue au WebMeeting **%{name}**! Le chat groupe est prêt."
  }
}